gglsbl_rest_client/__init__.py
gglsbl_rest_client/cli.py
gglsbl_rest_client/helpers.py
gglsbl_rest_client/etc/config.ini
gglsbl_rest_client-1.0.1.dist-info/LICENSE
gglsbl_rest_client-1.0.1.dist-info/METADATA
gglsbl_rest_client-1.0.1.dist-info/WHEEL
gglsbl_rest_client-1.0.1.dist-info/entry_points.txt
gglsbl_rest_client-1.0.1.dist-info/top_level.txt
gglsbl_rest_client-1.0.1.dist-info/RECORD
