Metadata-Version: 2.1
Name: gglsbl-rest-client
Version: 1.0.1
Summary: This is a simple python client wrapper for the [gglsbl-rest](https://github.com/mlsecproject/gglsbl-rest) service.
Home-page: https://github.com/seanmcfeely/gglsbl-rest-client
Author: Sean McFeely
Author-email: mcfeelynaes@gmail.com
License: Apache-2.0
Keywords: Information Security,Google SafeBrowsing
Platform: UNKNOWN
Classifier: Development Status :: 5 - Production/Stable
Classifier: Intended Audience :: Developers
Classifier: Intended Audience :: Information Technology
Classifier: Intended Audience :: Telecommunications Industry
Classifier: Operating System :: OS Independent
Classifier: License :: OSI Approved :: Apache Software License
Classifier: Programming Language :: Python :: 3 :: Only
Classifier: Programming Language :: Python :: 3
Classifier: Programming Language :: Python :: 3.0
Classifier: Programming Language :: Python :: 3.1
Classifier: Programming Language :: Python :: 3.2
Classifier: Programming Language :: Python :: 3.3
Classifier: Programming Language :: Python :: 3.4
Classifier: Programming Language :: Python :: 3.5
Classifier: Programming Language :: Python :: 3.6
Requires-Dist: requests
Requires-Dist: coloredlogs
